bayan/Functions.py
bayan/Weblog.py
bayan/__init__.py
bayan-1.0.0.dist-info/LICENSE
bayan-1.0.0.dist-info/METADATA
bayan-1.0.0.dist-info/WHEEL
bayan-1.0.0.dist-info/top_level.txt
bayan-1.0.0.dist-info/RECORD
