Metadata-Version: 2.1
Name: bayan
Version: 1.0.0
Summary: a library for get information from Bayan weblogs (https://blog.ir) 
Author-email: Hossein Ahmadi <4hmadiho55ein@gmail.com>
License: MIT License        
Project-URL: Homepage, https://github.com/ho55ein/bayan
Classifier: License :: OSI Approved :: MIT License
Classifier: Programming Language :: Python
Classifier: Programming Language :: Python :: 3
Requires-Python: >=3.5
License-File: LICENSE
Requires-Dist: beautifulsoup4
Requires-Dist: requests
Requires-Dist: lxml
